odoo10_addon_event_mail-10.0.1.0.0-py2.7-nspkg.pth
odoo/addons/event_mail/README.rst
odoo/addons/event_mail/__init__.py
odoo/addons/event_mail/__manifest__.py
odoo/addons/event_mail/i18n/es.po
odoo/addons/event_mail/models/__init__.py
odoo/addons/event_mail/models/event.py
odoo/addons/event_mail/models/event_mail.py
odoo/addons/event_mail/models/res_config.py
odoo/addons/event_mail/security/ir.model.access.csv
odoo/addons/event_mail/static/description/icon.png
odoo/addons/event_mail/tests/__init__.py
odoo/addons/event_mail/tests/test_event_mail.py
odoo/addons/event_mail/views/event_mail_view.xml
odoo/addons/event_mail/views/event_view.xml
odoo/addons/event_mail/views/res_config_view.xml
odoo10_addon_event_mail-10.0.1.0.0.dist-info/DESCRIPTION.rst
odoo10_addon_event_mail-10.0.1.0.0.dist-info/METADATA
odoo10_addon_event_mail-10.0.1.0.0.dist-info/RECORD
odoo10_addon_event_mail-10.0.1.0.0.dist-info/WHEEL
odoo10_addon_event_mail-10.0.1.0.0.dist-info/metadata.json
odoo10_addon_event_mail-10.0.1.0.0.dist-info/namespace_packages.txt
odoo10_addon_event_mail-10.0.1.0.0.dist-info/top_level.txt
